rvvup/__init__.py
rvvup/checkout_templates.py
rvvup/client.py
rvvup/events.py
rvvup/orders.py
rvvup/payment_methods.py
rvvup/webhooks.py
rvvup_python-0.1.0.dist-info/LICENSE
rvvup_python-0.1.0.dist-info/METADATA
rvvup_python-0.1.0.dist-info/WHEEL
rvvup_python-0.1.0.dist-info/RECORD
